{
  "datas": [
    {
      "data": [
        {
          "id": "38f2cc87-d30c-4e05-861c-5e48e8a6f0cd",
          "title": "打特戰",
          "date": "2024-08-21",
          "time": "20:17",
          "isDone": false,
          "isEditting": false
        },
        {
          "id": "cc5da630-e17a-49d1-9228-90bda28de895",
          "title": "haha",
          "date": "2024-08-20",
          "time": "19:34",
          "isDone": false,
          "isEditting": false
        },
        {
          "id": "23574270-6132-4ce2-98ed-c5fdab3910a2",
          "title": "手槍局",
          "date": "2024-07-30",
          "time": "19:43",
          "isDone": false,
          "isEditting": false
        }
      ],
      "id": "1"
    }
  ]
}